{
  "id": "277683322927183",
  "name": {
    "zh": "琦興餐廳"
  },
  "webpages": [
    {
      "url": "https://www.facebook.com/277683322927183/",
      "meta": {
        "id": "277683322927183",
        "name": "琦興餐廳",
        "about": "餐廳地址: 深水埗通州街288 - 300號, 順興閣地下",
        "category_list": [
          {
            "id": "512762212262409",
            "name": "Hong Kong Restaurant"
          }
        ],
        "single_line_address": "288-290通州街順興閣地下, Sham Shui Po, Hong Kong"
      }
    }
  ],
  "posts": [
    {
      "url": "https://www.facebook.com/permalink.php?story_fbid=413793399316174&id=277683322927183",
      "meta": {
        "sharedWith": "Public"
      }
    },
    {
      "url": "https://www.facebook.com/permalink.php?story_fbid=428166124545568&id=277683322927183",
      "meta": {
        "sharedWith": "Public"
      }
    },
    {
      "url": "https://www.facebook.com/permalink.php?story_fbid=489432988418881&id=277683322927183",
      "meta": {
        "sharedWith": "Public"
      }
    },
    {
      "url": "https://www.facebook.com/permalink.php?story_fbid=492690301426483&id=277683322927183",
      "meta": {
        "sharedWith": "Public"
      }
    },
    {
      "url": "https://www.facebook.com/permalink.php?story_fbid=505287803500066&id=277683322927183",
      "meta": {
        "sharedWith": "Public"
      }
    },
    {
      "url": "https://www.facebook.com/permalink.php?story_fbid=517580025604177&id=277683322927183",
      "meta": {
        "sharedWith": "Public"
      }
    }
  ],
  "tags": [
    "food"
  ],
  "places": [
    {
      "address": {
        "zh": "288-290通州街順興閣地下"
      },
      "googleMapsPlaceId": "ChIJPQ8XK6ABBDQRN1T-n0bOTzE",
      "coordinates": {
        "lat": 22.3281371,
        "lng": 114.1582523
      },
      "area": {
        "zh": "深水埗區"
      }
    }
  ],
  "yellowBlueMapIds": [
    {
      "type": "eat",
      "id": 1091
    }
  ]
}