{
  "id": "70srunaway2uk",
  "name": {
    "zh": "70後一家大細走難去英國"
  },
  "webpages": [
    {
      "url": "https://www.mcgazine.com"
    },
    {
      "url": "https://www.facebook.com/70srunaway2uk/",
      "meta": {
        "id": "109255787557883",
        "username": "70srunaway2uk",
        "name": "70後一家大細走難去英國",
        "about": "70s 揸BNO 一家大小走難去英國",
        "category_list": [
          {
            "id": "2700",
            "name": "Personal blog"
          }
        ],
        "website": "https://www.mcgazine.com/p/index-of-70.html",
        "link": "https://www.facebook.com/109255787557883"
      }
    }
  ],
  "posts": [
    {
      "url": "https://www.facebook.com/70srunaway2uk/posts/147877100362418",
      "meta": {
        "sharedWith": "Public"
      }
    },
    {
      "url": "https://www.facebook.com/70srunaway2uk/posts/153163583167103",
      "meta": {
        "sharedWith": "Public"
      }
    },
    {
      "url": "https://www.facebook.com/70srunaway2uk/posts/159574389192689",
      "meta": {
        "sharedWith": "Public"
      }
    },
    {
      "url": "https://www.facebook.com/70srunaway2uk/posts/166349305181864",
      "meta": {
        "sharedWith": "Public"
      }
    },
    {
      "url": "https://www.facebook.com/70srunaway2uk/posts/196222355527892",
      "meta": {
        "sharedWith": "Public"
      }
    }
  ],
  "tags": [
    "media"
  ]
}