{
  "id": "ajoyhk",
  "name": {
    "en": "A JOY",
    "zh": "桌悠"
  },
  "webpages": [
    {
      "url": "https://www.facebook.com/ajoyhk/",
      "meta": {
        "name": "A JOY 桌悠",
        "id": "450940738330447",
        "about": "A JOY 桌悠 位於荃灣, 5分鐘到荃灣廣場, 是荃灣唯一一間桌上遊戲專門店. 我們提供超過300款桌上遊戲任玩和導師指導。多款桌遊現貨/預訂 歡迎查詢。人少少book 枱玩又得 包場玩又得！",
        "categories": [
          "Art Gallery",
          "Cafe"
        ],
        "addr": "Room 1904 Ho Lik Centre, 66 Sha Tsui Road",
        "area": "Tsuen Wan, Hong Kong",
        "email": "ajoyhk@gmail.com",
        "tel": "67042789"
      }
    }
  ],
  "posts": [
    {
      "url": "https://www.facebook.com/ajoyhk/photos/a.742838079140710/2400228970068271",
      "meta": {
        "utime": "1564798589",
        "sharedWith": "Public"
      }
    },
    {
      "url": "https://www.facebook.com/ajoyhk/posts/2521189077972259",
      "meta": {
        "utime": "1570252563",
        "sharedWith": "Public"
      }
    },
    {
      "url": "https://www.facebook.com/ajoyhk/posts/2617205531703946",
      "meta": {
        "utime": "1573612582",
        "sharedWith": "Public"
      }
    }
  ],
  "tags": [
    "tabletopGame",
    "shop"
  ]
}