{
  "id": "BentomamaHK",
  "name": {
    "en": "Bentomama",
    "zh": "便當媽媽"
  },
  "webpages": [
    {
      "url": "https://www.facebook.com/BentomamaHK/",
      "meta": {
        "id": "2335204516750102",
        "username": "BentomamaHK",
        "name": "Bentomama 便當媽媽",
        "about": "「便當媽媽」最初對烹飪一竅不通。\n直到小孩上小學，無論如何也要媽媽親",
        "category_list": [
          {
            "id": "1802051720039034",
            "name": "Food delivery service"
          }
        ],
        "emails": [
          "bento.mama.tw@gmail.com"
        ],
        "single_line_address": "29C Pok Fu Lam Road, Hong Kong, Hong Kong",
        "link": "https://www.facebook.com/2335204516750102"
      }
    },
    {
      "url": "https://www.instagram.com/bento.mama.hk/",
      "meta": {
        "name": "Bento Ma Ma",
        "about": "「便當媽媽」最初對烹飪一竅不通。小時候，主要由姐姐負煮食。\n長大後，和先生兩口子忙於廣告制作工作。經常24時工作，煮食的需要離我更遠。\n直到小孩上小學，怎也不願吃外面的便當。無論如何也要媽媽親手煑。這樣就成了無休廚娘。兩個小孩快上中學，吃飽沒事幹的先生竟然慫恿我開外帶餐館？「便當媽媽」便這樣開始。"
      }
    }
  ],
  "posts": [
    {
      "url": "https://www.instagram.com/p/B-GX84tpgLQ/"
    },
    {
      "url": "https://www.instagram.com/p/B-ehhNCppDQ/"
    },
    {
      "url": "https://www.instagram.com/p/CG0euu1J_hs/"
    }
  ],
  "tags": [
    "food",
    "closed"
  ],
  "places": [
    {
      "address": {
        "en": "29C Pok Fu Lam Road"
      },
      "googleMapsPlaceId": "ChIJEW44uob_AzQRzMBUOojh84w",
      "coordinates": {
        "lat": 22.285072,
        "lng": 114.139015
      },
      "area": {
        "zh": "中西區"
      }
    }
  ],
  "yellowBlueMapIds": [
    {
      "type": "eat",
      "id": 1619
    }
  ]
}