{
  "id": "buslanes",
  "name": {
    "zh": "縱橫巴士綫",
    "en": "BusLanes"
  },
  "webpages": [
    {
      "url": "https://www.facebook.com/buslanes/",
      "meta": {
        "id": "1811729432394140",
        "username": "buslanes",
        "name": "縱橫巴士綫．BusLanes",
        "about": "延續 YouTube 頻道「縱橫巴士綫 BusLanes」高品質 和 優質巴士内容，保存 和 記錄 世界各地 富有地道特色 的 公共交通工具，推動大眾 和 愛好者 對巴士 嘅 欣賞文化與交流。",
        "category_list": [
          {
            "id": "1404",
            "name": "TV channel"
          }
        ],
        "website": "http://www.youtube.com/user/BusLanes",
        "link": "https://www.facebook.com/1811729432394140"
      }
    },
    {
      "url": "https://www.youtube.com/channel/UCGg5yxeAzZJq2YVP0H1j3EA",
      "meta": {
        "id": "UCGg5yxeAzZJq2YVP0H1j3EA",
        "name": "BusLanes",
        "about": "香港巴士，是香港主要公共交通工具之一，是目前香港每日載客量最多的公共交通系統，每日載客接近650萬人次。\n\n作為愛香港交通文化的朋友，我們製作「BusLanes．縱橫巴士綫」影片專頁，與大家一同分享各種珍貴的巴士片段。\n\n多謝支持！"
      }
    }
  ],
  "posts": [
    {
      "url": "https://www.facebook.com/buslanes/posts/2416278758605868",
      "meta": {
        "sharedWith": "Public"
      }
    },
    {
      "url": "https://www.facebook.com/buslanes/posts/2455623014671442",
      "meta": {
        "sharedWith": "Public"
      }
    }
  ],
  "tags": [
    "transport",
    "media"
  ]
}