{
  "id": "dingcut",
  "name": {
    "en": "DINGCUT"
  },
  "webpages": [
    {
      "url": "https://www.facebook.com/dingcut/",
      "meta": {
        "id": "209056912440453",
        "username": "dingcut",
        "name": "DINGCUT",
        "about": "One man band salon\n\n",
        "category_list": [
          {
            "id": "174177802634376",
            "name": "Hair Salon"
          }
        ],
        "single_line_address": "7/F., No.66 SAI YEUNG CHOI STREET, MONGKOK, KOWLOON, Hong Kong, Hong Kong",
        "website": "http://www.dingcut.com/",
        "link": "https://www.facebook.com/209056912440453"
      }
    },
    {
      "url": "https://www.instagram.com/dingcut.salon/",
      "meta": {
        "name": "DINGCUT Salon",
        "about": "💈Dingcut Salon 是由髮型師 @dingley_lui 開設的 一人運作髮型屋，One-man-band Hair Salon。\n☎️預約電話 2626 9845\n💬WhatsApp預約 9808 9404\n🕰 星期一至六 （1pm-10pm) 🔺星期日休息🔻"
      }
    }
  ],
  "posts": [
    {
      "url": "https://www.facebook.com/dingcut/posts/2479064148773040:0",
      "meta": {
        "sharedWith": "Public"
      }
    },
    {
      "url": "https://www.facebook.com/dingcut/posts/2575143795831741:0",
      "meta": {
        "sharedWith": "Public"
      }
    },
    {
      "url": "https://www.facebook.com/dingcut/posts/2764064796939639:0",
      "meta": {
        "sharedWith": "Public"
      }
    },
    {
      "url": "https://www.facebook.com/dingcut/posts/2769657576380361:0",
      "meta": {
        "sharedWith": "Public"
      }
    },
    {
      "url": "https://www.facebook.com/dingcut/posts/2792936184052500",
      "meta": {
        "sharedWith": "Public"
      }
    }
  ],
  "tags": [
    "salon",
    "shop"
  ],
  "places": [
    {
      "address": {
        "en": "7/F., No.66 SAI YEUNG CHOI STREET, MONGKOK, KOWLOON"
      },
      "googleMapsPlaceId": "ChIJ1Y3-yccABDQRfeSdRS7EpiI",
      "coordinates": {
        "lat": 22.318653,
        "lng": 114.170298
      },
      "area": {
        "zh": "油尖旺區"
      }
    }
  ],
  "yellowBlueMapIds": [
    {
      "type": "shop",
      "id": 1710
    }
  ]
}