{
  "id": "elmbook.bookshop",
  "name": {
    "zh": "榆林書店"
  },
  "webpages": [
    {
      "url": "https://www.elmbookhk.com"
    },
    {
      "meta": {
        "id": "717725661678807",
        "username": "elmbook.bookshop",
        "name": "榆林書店",
        "about": "榆林書店\n旺角西洋菜街樓上書店丨24週年誌慶丨為香港人精選中港台好書丨?",
        "category_list": [
          {
            "id": "387228845011016",
            "name": "Independent Bookstore"
          }
        ],
        "emails": [
          "elmbook@gmail.com"
        ],
        "single_line_address": "旺角西洋菜南街59號三樓, Mong Kok, Hong Kong",
        "website": "https://elmbookhk.com/",
        "link": "https://www.facebook.com/717725661678807"
      },
      "url": "https://www.facebook.com/elmbook.bookshop/"
    }
  ],
  "posts": [
    {
      "url": "https://www.facebook.com/elmbook.bookshop/posts/2196849320433093",
      "meta": {
        "sharedWith": "Public"
      }
    },
    {
      "url": "https://www.facebook.com/elmbook.bookshop/posts/2259201330864558",
      "meta": {
        "sharedWith": "Public"
      }
    },
    {
      "url": "https://www.facebook.com/elmbook.bookshop/posts/2284958004955557",
      "meta": {
        "sharedWith": "Public"
      }
    },
    {
      "url": "https://www.facebook.com/elmbook.bookshop/photos/a.717725725012134/2546092265508795"
    }
  ],
  "tags": [
    "book",
    "shop"
  ],
  "yellowBlueMapIds": [
    {
      "type": "shop",
      "id": 517
    }
  ],
  "places": [
    {
      "address": {
        "zh": "旺角西洋菜南街59號三樓"
      },
      "googleMapsPlaceId": "ChIJ0w85z8cABDQRw_GHsGTH2Rc",
      "coordinates": {
        "lat": 22.3190153,
        "lng": 114.1699286
      },
      "area": {
        "zh": "油尖旺區"
      }
    }
  ]
}