{
  "id": "fung_mei_noodles",
  "name": {
    "zh": "豐味車仔麵"
  },
  "webpages": [
    {
      "url": "https://www.facebook.com/fungmeinoodels/",
      "meta": {
        "id": "1987206434929021",
        "username": "fungmeinoodels",
        "name": "豐味車仔麵",
        "about": "香港味道 良心製造",
        "category_list": [
          {
            "id": "167954166588517",
            "name": "Diner"
          },
          {
            "id": "1848365298810025",
            "name": "Noodle House"
          }
        ],
        "single_line_address": "九龍旺角通菜街2A-2P號鴻光商埸地下2J號鋪, 00852 香港，香港",
        "website": "https://m.facebook.com/fungmeinoodels?_rdr"
      }
    },
    {
      "url": "https://www.instagram.com/fung_mei_noodles/",
      "meta": {
        "name": "豐味車仔麵",
        "about": "香港味道 良心製造￼"
      }
    }
  ],
  "posts": [
    {
      "url": "https://www.facebook.com/fungmeinoodels/photos/a.2021379888178342/2557354024580923",
      "meta": {
        "sharedWith": "Public"
      }
    }
  ],
  "tags": [
    "noodle"
  ],
  "places": [
    {
      "address": {
        "zh": "九龍旺角通菜街2A-2P號鴻光商埸地下2J號鋪"
      },
      "googleMapsPlaceId": "ChIJt5W_FL0BBDQRDuZabW599Ec",
      "coordinates": {
        "lat": 22.3161608,
        "lng": 114.1712956
      },
      "area": {
        "zh": "油尖旺區"
      }
    }
  ],
  "yellowBlueMapIds": [
    {
      "type": "eat",
      "id": 1783
    }
  ]
}