{
  "id": "HikerKit.siu",
  "name": {
    "zh": "山系の • 傑少"
  },
  "webpages": [
    {
      "meta": {
        "id": "258109244903798",
        "username": "HikerKit.siu",
        "name": "山系の • 傑少",
        "about": "要走遍香港每一個角落\nHK 90山峰 (Completed)",
        "category_list": [
          {
            "id": "2347428775505624",
            "name": "Digital creator"
          }
        ],
        "emails": [
          "hiker_kitsiu@hotmail.com"
        ],
        "website": "http://www.instagram.com/Hiker_kit.siu",
        "link": "https://www.facebook.com/258109244903798"
      },
      "url": "https://www.facebook.com/HikerKit.siu/"
    },
    {
      "url": "https://www.instagram.com/hiker_kit.siu/",
      "meta": {
        "name": "山系の • 傑少® K¡T ⛰️ 🖐🏼☝🏼",
        "about": "+852 𝙃.𝙆 🇭🇰 🤟🏼 長相廝守🎤 天秤男 ♎\n𝙃𝙞𝙠𝙞𝙣𝙜 | 𝘾𝙖𝙢𝙥𝙞𝙣𝙜 | 𝙎𝙥𝙤𝙧𝙩𝙮 | 𝙋𝙝𝙤𝙩𝙤\n⛰️ 🌅 🌄 ⛺ 🏋️ ⚽ 🥅 🚴🏼‍♂️ 📷 📸 🎮✈️\n✦沒 有 不 可 能 • 只 看 敢 不 敢✦"
      }
    }
  ],
  "posts": [
    {
      "url": "https://www.facebook.com/HikerKit.siu/photos/a.258397871541602/373856743329047",
      "meta": {
        "utime": "1564838667",
        "sharedWith": "Public"
      }
    },
    {
      "url": "https://www.facebook.com/HikerKit.siu/photos/a.258397871541602/382668372447884",
      "meta": {
        "utime": "1566441435",
        "sharedWith": "Public"
      }
    },
    {
      "url": "https://www.facebook.com/HikerKit.siu/photos/a.258397871541602/383416555706399",
      "meta": {
        "utime": "1566568088",
        "sharedWith": "Public"
      }
    }
  ],
  "tags": [
    "media"
  ]
}