{
  "id": "hikingwave",
  "name": {
    "zh": "浪行山野",
    "en": "Hiking Wave"
  },
  "webpages": [
    {
      "meta": {
        "id": "268583626923060",
        "username": "hikingwave",
        "name": "浪行山野  Hiking Wave",
        "about": "一班熱愛綠野之人組成的群體, 定期相約郊遊遠足, 享受戶外活動帶來的快樂",
        "category_list": [
          {
            "id": "2710",
            "name": "Recreation & sports website"
          },
          {
            "id": "268946656794071",
            "name": "Hiking Trail"
          }
        ],
        "emails": [
          "hikingwave@hotmail.com"
        ],
        "link": "https://www.facebook.com/268583626923060"
      },
      "url": "https://www.facebook.com/hikingwave/"
    }
  ],
  "posts": [
    {
      "url": "https://www.facebook.com/hikingwave/posts/704644256650326"
    },
    {
      "url": "https://www.facebook.com/hikingwave/photos/a.277967845984638/817896171991800"
    }
  ],
  "tags": [
    "media"
  ]
}