{
  "id": "japangel.ika",
  "name": {
    "zh": "和味天使小鋪"
  },
  "webpages": [
    {
      "url": "https://japangelmall.com"
    },
    {
      "url": "https://www.facebook.com/japangelmall/",
      "meta": {
        "name": "和味天使小鋪v2",
        "id": "102433448086361",
        "about": "一間賣女性服裝及用品的網店",
        "categories": [
          "Product/Service",
          "Personal Blog"
        ]
      }
    }
  ],
  "posts": [
    {
      "url": "https://www.facebook.com/japangelmall/posts/102496758080030",
      "meta": {
        "sharedWith": "Public"
      }
    },
    {
      "url": "https://www.facebook.com/japangelmall/posts/102556411407398",
      "meta": {
        "sharedWith": "Public"
      }
    }
  ],
  "tags": [
    "shop"
  ]
}