{
  "id": "JaseLabCookery",
  "name": {
    "en": "JaseLab Cookery"
  },
  "webpages": [
    {
      "url": "https://www.instagram.com/jaselabcookery/",
      "meta": {
        "website": "http://www.facebook.com/jaselabcookery/",
        "name": "JaseLab Cookery",
        "about": "This is a new account. Somehow the original one was deleted by Instagram, saying my account had violated the rules or sth...\nwhatever🤷🏻‍♂️"
      }
    },
    {
      "url": "https://www.facebook.com/JaseLabCookery/",
      "meta": {
        "id": "337196656469354",
        "username": "JaseLabCookery",
        "name": "JaseLab Cookery",
        "about": "We are a small restaurant with a big kitchen.\nAgain, we're small though, we still could have the right food & right place for you & your loved-ones. \nJoin us anytime you like mate! ",
        "category_list": [
          {
            "id": "198367566846946",
            "name": "Steakhouse"
          }
        ],
        "single_line_address": "Shui Che kwun lane, Yuen Long, Hong Kong",
        "website": "http://www.instagram.com/jaselab_cookery/",
        "link": "https://www.facebook.com/337196656469354"
      }
    }
  ],
  "posts": [
    {
      "url": "https://www.facebook.com/JaseLabCookery/posts/1060905980765081:0",
      "meta": {
        "sharedWith": "Public"
      }
    },
    {
      "url": "https://www.facebook.com/JaseLabCookery/posts/1062921047230241:0",
      "meta": {
        "sharedWith": "Public"
      }
    },
    {
      "url": "https://www.facebook.com/JaseLabCookery/posts/1171606499695028",
      "meta": {
        "sharedWith": "Public"
      }
    },
    {
      "url": "https://www.facebook.com/JaseLabCookery/posts/1173737866148558",
      "meta": {
        "sharedWith": "Public"
      }
    },
    {
      "url": "https://www.facebook.com/JaseLabCookery/posts/1195817013940643",
      "meta": {
        "sharedWith": "Public"
      }
    },
    {
      "url": "https://www.facebook.com/JaseLabCookery/photos/a.409369172585435/1196645753857769",
      "meta": {
        "sharedWith": "Public"
      }
    }
  ],
  "tags": [
    "food"
  ],
  "places": [
    {
      "address": {
        "en": "Shui Che Kwun Lane, Yuen Long"
      },
      "googleMapsPlaceId": "ChIJ_wNBtST7AzQRpXFsSyHO0AU",
      "coordinates": {
        "lat": 22.445005,
        "lng": 114.031773
      },
      "area": {
        "zh": "元朗區"
      }
    }
  ],
  "yellowBlueMapIds": [
    {
      "type": "eat",
      "id": 258
    }
  ]
}