{
  "id": "justmyshop0603",
  "name": {
    "en": "Just My Shop"
  },
  "webpages": [
    {
      "meta": {
        "id": "125749727528681",
        "username": "justmyshop0603",
        "name": "Just My Shop 文具精品雜貨店",
        "about": "Just My Shop 網上文具精品店，\n日本 韓國 台灣 代購。\n付款方法: 轉帳到 恆生 ",
        "category_list": [
          {
            "id": "200600219953504",
            "name": "Shopping & Retail"
          }
        ],
        "website": "https://www.instagram.com/just_my_shop/",
        "link": "https://www.facebook.com/125749727528681"
      },
      "url": "https://www.facebook.com/justmyshop0603/"
    },
    {
      "meta": {
        "name": "Jmys 文具精品雜貨店 wts: 5488 3995",
        "about": "由2013年開始，倆小口子的雜貨店，定期出國代購，主打日韓台卡通精品，不定期市集，100%正貨保證。順豐到付運費。\nLine / wechat id: jmyshop0603\nStore: 觀塘巧明街116-118街萬年工業大廈1樓C室O2O mall A4舖\n代購團: 待定"
      },
      "url": "https://www.instagram.com/just_my_shop/"
    }
  ],
  "posts": [
    {
      "url": "https://www.facebook.com/justmyshop0603/photos/a.320055781431407/1754358941334410"
    }
  ],
  "tags": [
    "shop"
  ],
  "yellowBlueMapIds": [
    {
      "type": "shop",
      "id": 1990
    }
  ]
}