{
  "id": "Lavabarrestaurant",
  "name": {
    "en": "LAVA Bar & Restaurant"
  },
  "webpages": [
    {
      "url": "https://www.facebook.com/Lavabarrestaurant/",
      "meta": {
        "id": "905836562844403",
        "username": "Lavabarrestaurant",
        "name": "LAVA Bar & Restaurant",
        "about": "西班牙菜。餐廳。酒吧,cocktails ",
        "category_list": [
          {
            "id": "188360891207745",
            "name": "Modern European Restaurant"
          }
        ],
        "link": "https://www.facebook.com/905836562844403"
      }
    },
    {
      "url": "https://www.instagram.com/lava.tst/",
      "meta": {
        "name": "Lava",
        "about": "Spanish food, cocktails , wine , music, party. Dj"
      }
    }
  ],
  "posts": [
    {
      "url": "https://www.facebook.com/Lavabarrestaurant/photos/a.909230139171712/2420392071388837/",
      "meta": {
        "sharedWith": "Public"
      }
    },
    {
      "url": "https://www.facebook.com/Lavabarrestaurant/posts/2564617036966339/",
      "meta": {
        "sharedWith": "Public"
      }
    }
  ],
  "tags": [
    "bar"
  ],
  "places": [
    {
      "address": {
        "zh": "九龍尖沙咀金巴利道金巴利廣場4樓"
      },
      "googleMapsPlaceId": "ChIJOen1gu4ABDQR8FzVe-ehVu4",
      "coordinates": {
        "lat": 22.3009932,
        "lng": 114.1741248
      },
      "area": {
        "zh": "油尖旺區"
      }
    }
  ],
  "yellowBlueMapIds": [
    {
      "type": "eat",
      "id": 455
    }
  ]
}