{
  "id": "mamasdumpling",
  "name": {
    "zh": "元朗有得餃"
  },
  "webpages": [
    {
      "meta": {
        "id": "138380349654695",
        "username": "mamasdumpling",
        "name": "元朗有得餃",
        "about": "我們是元朗有得餃.\n類別 :港式小食/熟食店、餛飩/餃子",
        "category_list": [
          {
            "id": "188334264523313",
            "name": "Deli"
          },
          {
            "id": "174483852595760",
            "name": "Chinese Restaurant"
          }
        ],
        "single_line_address": "元朗建業街47 49號地舖, Hong Kong，Yuen Long",
        "website": "https://s.openrice.com/QrbS0vTi900~uzSoDAA",
        "link": "https://www.facebook.com/138380349654695"
      },
      "url": "https://www.facebook.com/mamasdumpling/"
    }
  ],
  "posts": [
    {
      "url": "https://www.facebook.com/mamasdumpling/photos/a.138557352970328/1421702127989171"
    },
    {
      "url": "https://www.facebook.com/mamasdumpling/posts/1400684630090921"
    }
  ],
  "tags": [
    "food"
  ],
  "yellowBlueMapIds": [
    {
      "type": "eat",
      "id": 815
    }
  ],
  "places": [
    {
      "address": {
        "zh": "元朗建業街47 49號地舖"
      },
      "googleMapsPlaceId": "ChIJxRxow-v7AzQRAOt2tsrrVnA",
      "coordinates": {
        "lat": 22.4420153,
        "lng": 114.0316009
      },
      "area": {
        "zh": "元朗區"
      }
    }
  ]
}