{
  "id": "meatdee",
  "name": {
    "en": "meatdee"
  },
  "webpages": [
    {
      "url": "https://www.facebook.com/meatdee/",
      "meta": {
        "id": "134241836642867",
        "username": "meatdee",
        "name": "meatdee",
        "about": "@牛肉大叔 分享用不同産地、不同品種、品牌嘅肉類。品質、切法，煮法同?",
        "category_list": [
          {
            "id": "1562965077339698",
            "name": "Food & Beverage"
          },
          {
            "id": "132852590115660",
            "name": "Kitchen/cooking"
          },
          {
            "id": "1817904601806120",
            "name": "Video Creator"
          }
        ],
        "emails": [
          "deeliu@newkwokwahmeat.com"
        ],
        "website": "https://www.youtube.com/c/MeatDee",
        "link": "https://www.facebook.com/134241836642867"
      }
    },
    {
      "url": "https://www.instagram.com/meat_dee/",
      "meta": {
        "website": "http://tellonym.me/meatdee/",
        "name": "Dee Liu 아띠",
        "about": "#youtuber #butcher #meatlover #traveler\n@🇰🇷 #foodexporter\n@🇭🇰 #meatimporter #meatshop #banchan\nGym @uncle_meatdee 📸🤳 @little_thing_big_love\n最❤️買牛"
      }
    },
    {
      "url": "https://www.youtube.com/channel/UC1aMRX7uvo5m-7S09QyxVAQ",
      "meta": {
        "id": "UC1aMRX7uvo5m-7S09QyxVAQ",
        "location": "Hong Kong",
        "name": "Meat Dee",
        "about": ""
      }
    }
  ],
  "posts": [
    {
      "url": "https://www.instagram.com/p/B1TRlvAh3am/"
    },
    {
      "url": "https://www.facebook.com/meatdee/photos/a.1531360496930987/3986626621404350/?type=3"
    },
    {
      "url": "https://www.facebook.com/meatdee/posts/4202415106492166/"
    }
  ],
  "tags": [
    "food",
    "media"
  ]
}