{
  "id": "Mike.lamkingnam",
  "name": {
    "en": "MIKE LAM",
    "zh": "林景楠"
  },
  "webpages": [
    {
      "url": "https://www.facebook.com/Mike.lamkingnam/",
      "meta": {
        "name": "林景楠 MIKE LAM",
        "id": "103385657854752",
        "about": "ABOUTHAI 阿布泰國生活百貨老闆的個人專頁",
        "categories": [
          "Personal Blog"
        ]
      }
    }
  ],
  "posts": [
    {
      "url": "https://www.facebook.com/Mike.lamkingnam/posts/112607733599211",
      "meta": {
        "sharedWith": "Public"
      }
    },
    {
      "url": "https://www.facebook.com/Mike.lamkingnam/posts/131228188403832",
      "meta": {
        "sharedWith": "Public"
      }
    },
    {
      "url": "https://www.facebook.com/Mike.lamkingnam/posts/134423871417597",
      "meta": {
        "sharedWith": "Public"
      }
    },
    {
      "url": "https://www.facebook.com/Mike.lamkingnam/posts/150456409814343",
      "meta": {
        "sharedWith": "Public"
      }
    },
    {
      "url": "https://www.facebook.com/Mike.lamkingnam/posts/151431263050191",
      "meta": {
        "sharedWith": "Public"
      }
    }
  ],
  "tags": [
    "publicfigure"
  ],
  "alias": [
    "103385657854752"
  ]
}