{
  "id": "monzoneworks",
  "name": {
    "zh": "怪模工房",
    "en": "Mon-Zone Works"
  },
  "webpages": [
    {
      "url": "https://www.facebook.com/monzoneworks/",
      "meta": {
        "id": "583914938373543",
        "username": "monzoneworks",
        "name": "怪模工房Mon-Zone Works",
        "about": "外接書刋插圖丶專欄寫作丶模型製作、塗裝及首辦雕刻等。\n 並開辦繪畫丶?",
        "category_list": [
          {
            "id": "2601",
            "name": "School"
          }
        ],
        "link": "https://www.facebook.com/583914938373543"
      }
    },
    {
      "url": "https://www.instagram.com/monzoneworks/",
      "meta": {
        "name": "mon-zone Works怪模工房",
        "about": "主持人余漢雲Bobyu，於香港從事插畫，漫畫編繪，模型塗裝、手辦雕刻，及教學工作，舉辦電繪及Zbrush3D雕刻課程等。［Gameweekly 電玩雜誌＂怪模教室＂］專欄作者，［怪模工房］手辦製作室主持人，［童夢漫畫教室］專門學校校長。#怪模工房"
      }
    }
  ],
  "posts": [
    {
      "url": "https://www.facebook.com/monzoneworks/posts/2217800641651623",
      "meta": {
        "sharedWith": "Public"
      }
    },
    {
      "url": "https://www.facebook.com/monzoneworks/posts/2218096108288743",
      "meta": {
        "sharedWith": "Public"
      }
    },
    {
      "url": "https://www.facebook.com/monzoneworks/posts/2221033137995040",
      "meta": {
        "sharedWith": "Public"
      }
    },
    {
      "url": "https://www.facebook.com/monzoneworks/posts/2315754851856201",
      "meta": {
        "sharedWith": "Public"
      }
    },
    {
      "url": "https://www.facebook.com/monzoneworks/posts/2507586076006410",
      "meta": {
        "sharedWith": "Public"
      }
    }
  ],
  "tags": [
    "artist",
    "toy",
    "shop"
  ]
}