{
  "id": "ofarmhk",
  "name": {
    "en": "O-Farm"
  },
  "webpages": [
    {
      "url": "https://www.facebook.com/ofarmhk/",
      "meta": {
        "id": "167515199983305",
        "username": "ofarmhk",
        "name": "O-Farm",
        "about": "永續生活，由個人出發。-- www.o-farm.com ; ofarm@o-farm.com\n",
        "category_list": [
          {
            "id": "150815208309028",
            "name": "Farm"
          },
          {
            "id": "1874409019452971",
            "name": "Locality"
          }
        ],
        "emails": [
          "ofarm@o-farm.com"
        ],
        "single_line_address": "O-Farm老農田有機農場, 鶴藪排, 鶴藪郊野徑側, 丹竹坑,, Гонконг, Гонконг",
        "website": "http://www.o-farm.com/",
        "link": "https://www.facebook.com/167515199983305"
      }
    },
    {
      "url": "https://www.instagram.com/ofarmhk/",
      "meta": {
        "website": "http://www.facebook.com/ofarmhk",
        "name": "O-farm",
        "about": "Back to sustainable farming life"
      }
    }
  ],
  "posts": [
    {
      "url": "https://www.facebook.com/ofarmhk/posts/2180370205364451",
      "meta": {
        "sharedWith": "Public"
      }
    },
    {
      "url": "https://www.facebook.com/ofarmhk/posts/2182685591799579",
      "meta": {
        "sharedWith": "Public"
      }
    },
    {
      "url": "https://www.facebook.com/ofarmhk/posts/2191471914254280",
      "meta": {
        "sharedWith": "Public"
      }
    },
    {
      "url": "https://www.facebook.com/ofarmhk/posts/2277163912351746",
      "meta": {
        "sharedWith": "Public"
      }
    }
  ],
  "tags": [
    "farm",
    "foodStore"
  ],
  "places": [
    {
      "address": {
        "en": "San Uk Tsai Village, Tan Chuk Hang"
      },
      "googleMapsPlaceId": "ChIJRTmhLYgJBDQRMfvvOEhv6u0",
      "coordinates": {
        "lat": 22.508292,
        "lng": 114.17698
      },
      "area": {
        "zh": "北區"
      }
    }
  ],
  "yellowBlueMapIds": [
    {
      "type": "shop",
      "id": 1617
    }
  ]
}