{
  "id": "Onescafehk",
  "name": {
    "en": "One's Cafe",
    "zh": "1仔冰室"
  },
  "webpages": [
    {
      "meta": {
        "id": "356781328220869",
        "username": "Onescafehk",
        "name": "1仔冰室 One's Cafe",
        "about": "1仔便當one's bento\n九龍灣 環球工商大廈地下2B舖 宏開道8號\nFood Order:\nTel: 311 88 333  \nWhatsapp: 649 55 111",
        "category_list": [
          {
            "id": "192108214153222",
            "name": "Breakfast & Brunch Restaurant"
          },
          {
            "id": "512762212262409",
            "name": "Hong Kong Restaurant"
          },
          {
            "id": "128673187201735",
            "name": "Coffee Shop"
          }
        ],
        "emails": [
          "onescafe.cgl@gmail.com"
        ],
        "single_line_address": "香港九龍紅磡必嘉街92-112號 紅磡灣中心地下9C鋪, Kowloon, Hong Kong"
      },
      "url": "https://www.facebook.com/Onescafehk/"
    },
    {
      "url": "https://www.instagram.com/onescafehk/",
      "meta": {
        "name": "1仔冰室"
      }
    }
  ],
  "posts": [
    {
      "url": "https://www.instagram.com/p/B53-E4NDKdl/"
    },
    {
      "url": "https://www.instagram.com/p/B58EtBtjZEN/"
    },
    {
      "url": "https://www.instagram.com/p/B5-qVfljCsV/"
    },
    {
      "url": "https://www.instagram.com/p/B6IslCmj5cu/"
    }
  ],
  "tags": [
    "food"
  ],
  "places": [
    {
      "address": {
        "zh": "香港九龍紅磡必嘉街92-112號 紅磡灣中心地下9C鋪"
      },
      "googleMapsPlaceId": "ChIJg1k5RBoBBDQRqGg-YmLg16E",
      "coordinates": {
        "lat": 22.3058827,
        "lng": 114.1851604
      },
      "area": {
        "zh": "九龍城區"
      }
    }
  ],
  "yellowBlueMapIds": [
    {
      "type": "eat",
      "id": 744
    },
    {
      "type": "eat",
      "id": 5240
    }
  ]
}