{
  "id": "practicemoment",
  "name": {
    "en": "PracticeMoment"
  },
  "webpages": [
    {
      "meta": {
        "id": "1487370451535338",
        "about": "PracticeMoment\n樂器課程,鼓房練習房租用及樂器售賣\n地址： 元朗宏發徑8號宏發商場2樓17號舖...\n\n\nSee more",
        "categories": [
          "Musical instrument store",
          "Film & music shop",
          "Education"
        ],
        "addr": "元朗宏發徑8號宏發商場2樓17號舖",
        "area": "Yuen Long",
        "email": "practicemoment@gmail.com",
        "tel": "93450777"
      },
      "url": "https://www.facebook.com/practicemoment/"
    },
    {
      "url": "https://www.instagram.com/practicemoment_ig/"
    }
  ],
  "posts": [
    {
      "url": "https://www.facebook.com/practicemoment/posts/2439881972950843"
    },
    {
      "url": "https://www.facebook.com/practicemoment/posts/2320968104842231"
    }
  ],
  "tags": [
    "music",
    "shop"
  ]
}