{
  "id": "saiwancybercafe",
  "name": {
    "zh": "西環網吧"
  },
  "webpages": [
    {
      "url": "https://www.facebook.com/saiwancybercafe/",
      "meta": {
        "id": "109979359053563",
        "username": "saiwancybercafe",
        "name": "西環網吧",
        "about": "西環,德輔道西436A,均益大廈第一期地下7號舖\n全年24小時服務,價錢平,免費wifi,玩遊戲又快又順.耳筒供應,場地清潔有管理.員工友善服務好,有問題立即處理.有小食,杯麵,汽水,電腦用品及多功能鉗",
        "category_list": [
          {
            "id": "2500",
            "name": "Local Business"
          }
        ],
        "link": "https://www.facebook.com/109979359053563"
      }
    }
  ],
  "posts": [
    {
      "url": "https://www.facebook.com/saiwancybercafe/posts/2542696405781834",
      "meta": {
        "sharedWith": "Public"
      }
    }
  ],
  "tags": [
    "videoGame",
    "shop"
  ],
  "places": [
    {
      "address": {
        "zh": "西營盤，德輔道西430-440A，均益大廈第一期，地下7號舖"
      },
      "googleMapsPlaceId": "ChIJt7pYfIP_AzQREbia3FFlhSo",
      "coordinates": {
        "lat": 22.2868704,
        "lng": 114.1345241
      },
      "area": {
        "zh": "中西區"
      }
    }
  ],
  "yellowBlueMapIds": [
    {
      "type": "shop",
      "id": 353
    }
  ]
}