{
  "id": "secrettourhk",
  "name": {
    "en": "Secret Tour Hong Kong"
  },
  "webpages": [
    {
      "url": "https://secrettour.hk"
    },
    {
      "url": "https://www.facebook.com/secrettourhk/",
      "meta": {
        "id": "137673536295835",
        "username": "secrettourhk",
        "name": "Secret Tour Hong Kong",
        "about": "One of the Bees Group. Brand Experience Agency, offering ATL, BTL, Digital and Social Media Management. \ninquiry: hello@secrettourhk.com",
        "category_list": [
          {
            "id": "2500",
            "name": "Local Business"
          }
        ],
        "website": "http://secrettour.hk/",
        "link": "https://www.facebook.com/137673536295835"
      }
    },
    {
      "url": "https://www.instagram.com/secrettourhk/",
      "meta": {
        "name": "Secret Tour Hong Kong"
      }
    }
  ],
  "posts": [
    {
      "url": "https://www.facebook.com/secrettourhk/posts/2521258214604010",
      "meta": {
        "sharedWith": "Public"
      }
    },
    {
      "url": "https://www.facebook.com/secrettourhk/posts/3329454713784352",
      "meta": {
        "sharedWith": "Public"
      }
    }
  ],
  "tags": [
    "advertisingAgency",
    "shop"
  ],
  "places": [
    {
      "address": {
        "en": "1/F, Lok's Industrial Building, 204 Tsat Tsz Mui Road"
      },
      "googleMapsPlaceId": "ChIJGddBPA4BBDQRUDruH5Kpsxo",
      "coordinates": {
        "lat": 22.2908962,
        "lng": 114.2075872
      },
      "area": {
        "zh": "東區"
      }
    }
  ]
}