{
  "id": "slowcookgoodfood2018",
  "name": {
    "en": "Slow Cook Good Food"
  },
  "webpages": [
    {
      "url": "https://slowcookgoodfood.com"
    },
    {
      "url": "https://www.facebook.com/slowcookgoodfood2018/",
      "meta": {
        "name": "Slow Cook Good Food",
        "id": "239658746579186",
        "categories": [
          "French Restaurant",
          "Asian Fusion Restaurant"
        ],
        "addr": "G/F, 12 Kau U Fong, Central",
        "area": "HK Hong Kong",
        "email": "slowcookgoodfood@gmail.com",
        "tel": "26868101"
      }
    },
    {
      "url": "https://www.instagram.com/slowcookgoodfood/",
      "meta": {
        "name": "慢煮兩餐 - 新中環特色餐館",
        "about": "1. 榮獲《飲食男女》頒發【注目新店推介】2018 MUST GO RESTAURANT.\n2. 提供全日餐飲給予天馬影視所有演員，該公司即將推出新片：葉問四\n3. 由即日起：歡迎任何慈善團體申請”星期六免費午餐”\n詳情可致電：2686 8101\n中環九如坊12號"
      }
    }
  ],
  "posts": [
    {
      "url": "https://hk.lifestyle.appledaily.com/etw/magazine/article/20190610/3_59699172/-%E5%8F%8D%E9%80%81%E4%B8%AD-12-6%E7%BD%B7%E5%B7%A5%E4%B8%80%E5%A4%A9-Caf%C3%A9%E9%AD%9A%E8%9B%8B%E6%AA%94%E5%B0%8F%E9%A3%9F%E5%BA%97%E9%BD%8A%E9%BD%8A%E5%8A%A0%E6%B2%B9"
    },
    {
      "url": "https://hk.entertainment.appledaily.com/entertainment/20190802/QVC7N666RVTSAFAPT64V7QBPSI/",
      "summary": {
        "zh": "【8.5大罷工】吳啟明支持8.5罷巿 中環新店歡迎示威者入內休息 ｜ 即時 ｜ 娛樂 ｜ 20190802"
      }
    }
  ],
  "tags": [
    "food"
  ]
}