{
  "id": "tarenchan",
  "name": {
    "en": "Taren Chan Illustration",
    "zh": "小琪亂畫室"
  },
  "webpages": [
    {
      "url": "https://www.instagram.com/tarenchan/",
      "meta": {
        "website": "http://www.linktr.ee/tarenchan",
        "name": "tarenchan",
        "about": "UK based HK illustrator\nFreelance project collaborations are welcomed\n在英港人歡迎商談合作"
      }
    },
    {
      "url": "https://www.facebook.com/1457712000999773/",
      "meta": {
        "id": "1457712000999773",
        "name": "小琪亂畫室 Taren Chan Illustration",
        "about": "兩子之母，盼望除了用文字或照片，還可以圖畫記錄下自己對孩子的愛。",
        "category_list": [
          {
            "id": "2700",
            "name": "Personal blog"
          }
        ],
        "website": "http://www.tarenchan.com/",
        "link": "https://www.facebook.com/1457712000999773"
      }
    }
  ],
  "posts": [
    {
      "url": "https://www.facebook.com/1457712000999773/posts/1968069233297378/"
    },
    {
      "url": "https://www.facebook.com/1457712000999773/posts/1969832403121061/"
    },
    {
      "url": "https://www.facebook.com/1457712000999773/posts/1999174830186818/"
    }
  ],
  "tags": [
    "artist",
    "shop"
  ],
  "places": [
    {
      "area": {
        "zh": "英國"
      }
    }
  ]
}