{
  "id": "Teacirclegroup",
  "name": {
    "en": "Royaltea",
    "zh": "皇茶"
  },
  "webpages": [
    {
      "meta": {
        "id": "417399898629601",
        "username": "royalteahk.RTHK",
        "name": "Royaltea.HK 皇茶香港",
        "about": "我們是 Royal Tea HK\n天圓地方茶葉圓尖幼粗枝各有熟地，茂盛滋長。Be a part of the center \n\n將世界各地的好茶帶到香港，創造品茶潮流 ‘Fashion Tea’\n\n",
        "category_list": [
          {
            "id": "203462172997785",
            "name": "Tea Room"
          }
        ],
        "emails": [
          "cs.royalteahk@gmail.com"
        ],
        "single_line_address": "旺角廣華街1號仁安大廈地下22號鋪（向登打士街）, 香港"
      },
      "url": "https://www.facebook.com/royalteahk.RTHK/"
    },
    {
      "url": "https://www.instagram.com/royaltea.hk/",
      "meta": {
        "name": "Royalteahk",
        "about": "香港加油 • 遍地開花 ·同路人·金魔法"
      }
    }
  ],
  "posts": [
    {
      "url": "https://www.facebook.com/417399898629601/posts/1019716111731307"
    },
    {
      "url": "https://www.facebook.com/417399898629601/posts/1010271519342433"
    },
    {
      "url": "https://www.facebook.com/417399898629601/videos/2533328406953076"
    }
  ],
  "tags": [
    "food",
    "taiwanese"
  ],
  "places": [
    {
      "address": {
        "zh": "旺角廣華街1號仁安大廈22號鋪（向登打士街）"
      },
      "googleMapsPlaceId": "ChIJrTdplMYABDQRtYIGRVsGjxg",
      "coordinates": {
        "lat": 22.3157934,
        "lng": 114.1724344
      },
      "area": {
        "zh": "油尖旺區"
      }
    }
  ],
  "yellowBlueMapIds": [
    {
      "type": "eat",
      "id": 1291
    }
  ]
}