{
  "id": "threesistersss",
  "name": {
    "zh": "三小鬼/三姐妹"
  },
  "webpages": [
    {
      "meta": {
        "id": "104892254372797",
        "username": "threesistersss",
        "name": "三姐妹",
        "about": "外賣店",
        "category_list": [
          {
            "id": "273819889375819",
            "name": "Restaurant"
          }
        ],
        "single_line_address": "利東邨街市48-50號, Hong Kong, Hong Kong"
      },
      "url": "https://www.facebook.com/104892254372797/"
    }
  ],
  "posts": [
    {
      "url": "https://www.thestandnews.com/politics/%E9%B4%A8%E8%84%B7%E6%B4%B2%E9%BB%83%E5%BA%97-%E4%B8%89%E5%A7%90%E5%A6%B9-%E8%A2%AB%E6%B7%8B%E6%B2%B9-%E6%9B%BE%E8%A2%AB%E6%8C%87%E6%8E%A7%E7%82%BA-%E5%8D%97%E5%8D%80%E9%98%BB%E8%A1%97%E5%A0%B5%E8%B7%AF%E5%8F%AC%E9%9B%86%E4%BA%BA/"
    }
  ],
  "tags": [
    "food"
  ],
  "places": [
    {
      "address": {
        "zh": "香港仔大道90號"
      },
      "googleMapsPlaceId": "Eig5MCBBYmVyZGVlbiBNYWluIFJkLCBBYmVyZGVlbiwgSG9uZyBLb25nIjASLgoUChIJF-oY8BwABDQRs8lPUiEyPQMQWioUChIJtcfRNQMABDQRE1LHntt5YoA",
      "coordinates": {
        "lat": 22.2471854,
        "lng": 114.1574677
      },
      "area": {
        "zh": "南區"
      }
    }
  ],
  "yellowBlueMapIds": [
    {
      "type": "eat",
      "id": 506
    }
  ],
  "alias": [
    "104892254372797"
  ]
}