{
  "id": "Trust.HairSalon.TaiPo",
  "name": {
    "en": "TrustHair salon"
  },
  "webpages": [
    {
      "url": "https://www.facebook.com/Trust.HairSalon.TaiPo/",
      "meta": {
        "id": "879972125443373",
        "username": "Trust.HairSalon.TaiPo",
        "name": "еӨ§еҹ” TrustHair salon",
        "about": "вңЁOpening Hours: MON-SUN 10:30-20:30рҹ’Ҳ\nвҶ еӨ§еҹ”зёҪеә—пҪңеӨ§еҹ”жҳҢйҒӢдёӯеҝғе•Ҷе ҙ1жЁ“41иҷҹиҲ–\nвҶ жЁӮеҜҢеә—пҪңжЁӮеҜҢе»Је ҙA еҚҖ 2жЁ“2128иҷҹиҲ–\nВ·\nрҹ”ҚжӯЎиҝҺinboxжҹҘи©ўй җзҙ„",
        "category_list": [
          {
            "id": "174177802634376",
            "name": "Hair Salon"
          }
        ],
        "single_line_address": "еӨ§еҹ”жҳҢйҒӢдёӯеҝғ1жЁ“41иҷҹ, 852 Hong Kong, Hong Kong",
        "link": "https://www.facebook.com/879972125443373"
      }
    },
    {
      "url": "https://www.instagram.com/trust_hair_salon/",
      "meta": {
        "website": "https://www.instagram.com/trust_hair_salon/",
        "name": "рҹ’ҲTrustHairSalonпҪңеӨ§еҹ”пҪңжЁӮеҜҢпҪңжўЁиҠұй ӯпҪңзӣҙзҷӮпҪңзҶұзҷӮпҪңеҶ·зҷӮпҪңй ӯзҡ®иӯ·зҗҶпҪңй ӯй«®иӯ·зҗҶпҪңжҢ‘жҹ“пҪңжҹ“й«®з„—жІ№",
        "about": "вңЁбҙҸбҙҳбҙҮЙҙЙӘЙҙЙў КңбҙҸбҙңКҖs: бҙҚбҙҸЙҙ-sбҙңЙҙ рқҹҸрқҹҺ:рқҹ‘рқҹҺ-рқҹҗрқҹҺ:рқҹ‘рқҹҺрҹ’Ў\nвҶ еӨ§еҹ”зёҪеә—пҪңеӨ§еҹ”жҳҢйҒӢдёӯеҝғе•Ҷе ҙ1жЁ“41иҷҹиҲ–\nвҶ жЁӮеҜҢеә—пҪңжЁӮеҜҢе»Је ҙ2жЁ“2128иҷҹиҲ– (зұҢеӮҷдёӯвӢҜрҹ«Ў)\nВ·\nрҹ”ҚжӯЎиҝҺDMжҹҘи©ўй җзҙ„"
      }
    }
  ],
  "posts": [
    {
      "url": "https://www.facebook.com/Trust.HairSalon.TaiPo/posts/2293979554042616",
      "meta": {
        "sharedWith": "Public"
      }
    },
    {
      "url": "https://www.facebook.com/Trust.HairSalon.TaiPo/posts/2295016763938895",
      "meta": {
        "sharedWith": "Public"
      }
    },
    {
      "url": "https://www.facebook.com/Trust.HairSalon.TaiPo/posts/2466270660146837",
      "meta": {
        "sharedWith": "Public"
      }
    },
    {
      "url": "https://www.facebook.com/Trust.HairSalon.TaiPo/posts/2527603094013593",
      "meta": {
        "sharedWith": "Public"
      }
    }
  ],
  "tags": [
    "salon"
  ],
  "places": [
    {
      "address": {
        "zh": "еӨ§еҹ”жҳҢйҒӢдёӯеҝғ1жЁ“41иҷҹ"
      },
      "googleMapsPlaceId": "ChIJ149WjEcIBDQRfy7WiP0TBYA",
      "coordinates": {
        "lat": 22.4525376,
        "lng": 114.1680803
      },
      "area": {
        "zh": "еӨ§еҹ”еҚҖ"
      }
    },
    {
      "address": {
        "zh": "жЁӮеҜҢе»Је ҙ2жЁ“2128иҷҹиҲ–"
      },
      "googleMapsPlaceId": "ChIJJR6V5SgHBDQRw2EJd1O7vMg",
      "coordinates": {
        "lat": 22.3383244,
        "lng": 114.1872329
      },
      "area": {
        "zh": "й»ғеӨ§д»ҷеҚҖ"
      }
    }
  ],
  "yellowBlueMapIds": [
    {
      "type": "shop",
      "id": 574
    }
  ]
}