{
  "id": "ukimms",
  "name": {
    "zh": "英倫移民",
    "en": "UK Immigration Specialist"
  },
  "webpages": [
    {
      "url": "https://www.ukimms.com"
    },
    {
      "url": "https://www.facebook.com/mhtjanine/",
      "meta": {
        "id": "373666862984438",
        "username": "mhtjanine",
        "name": "英倫移民 Janine Miu",
        "about": "《英倫移民》創辦人，英國大律師，畢業於英國倫敦城市大學法律碩士、林肯大學法律學士。公司成立十年，專注提供英國、歐盟及澳洲移民服務，其專業服務屢受傳媒專訪，如路透社、彭博、金融時報、BBC、ViuTV等。",
        "category_list": [
          {
            "id": "1723986644540644",
            "name": "Immigration Lawyer"
          }
        ],
        "website": "https://www.ukimms.com/",
        "link": "https://www.facebook.com/373666862984438"
      }
    },
    {
      "url": "https://www.instagram.com/janinemiu_ukimms/",
      "meta": {
        "website": "http://www.ukimms.com/",
        "name": "英倫移民 Janine Miu",
        "about": "🇬🇧 英倫移民創辦人\n💌著有出版作品\n《只想追趕生命𥚃一分一秒 移民英國解讀101》\n《擁有同樣寄望 香港人移居英國的故事》\n《離開以後 妳還好嗎》"
      }
    },
    {
      "url": "https://www.youtube.com/channel/UCrRlTHs9HSkq7TUkBHOWqnw",
      "meta": {
        "id": "UCrRlTHs9HSkq7TUkBHOWqnw",
        "name": "英倫移民 Janine Miu",
        "about": "【投資海外樓】為您分析英國熱門地區，介紹名校區屋苑，著名發展商獨立屋及鐵路上蓋全新住宅等。"
      }
    }
  ],
  "posts": [
    {
      "url": "https://www.facebook.com/mhtjanine/posts/909236246094161/"
    },
    {
      "url": "https://www.facebook.com/mhtjanine/posts/983994618618323/"
    }
  ],
  "tags": [
    "shop"
  ]
}