{
  "id": "WoKee",
  "name": {
    "zh": "和記餐廳"
  },
  "webpages": [
    {
      "meta": {
        "name": "和記餐廳-灣仔店",
        "id": "1354974464582024",
        "about": "將本土音樂及文化crossover 的茶餐廳",
        "categories": [
          "Hong Kong Restaurant",
          "Diner"
        ],
        "addr": "灣仔謝斐道392-402號維新大厦地下E鋪",
        "area": "0 Wan Chai",
        "tel": "28939880"
      },
      "url": "https://www.facebook.com/137752920269918/"
    },
    {
      "url": "https://www.facebook.com/WoKee/",
      "meta": {
        "name": "和記餐廳-西灣河",
        "id": "1429276877299020",
        "categories": [
          "Diner"
        ],
        "addr": "香港西灣河聖十字徑38號鴻恩大厦7號地舖",
        "area": "852 Hong Kong",
        "email": "wokeeswh@gmail.com",
        "tel": "25676338"
      }
    },
    {
      "url": "https://www.instagram.com/wookee_wanchai/",
      "meta": {
        "name": "和記餐廳(灣仔店)",
        "about": "地址灣仔謝斐道392號維新大厦地下E鋪\n電話28939880,28939660\n營業時間7am~7pm"
      }
    }
  ],
  "posts": [
    {
      "url": "https://www.facebook.com/permalink.php?story_fbid=435981757113698&id=137752920269918"
    },
    {
      "url": "https://www.facebook.com/permalink.php?story_fbid=440886313289909&id=137752920269918"
    }
  ],
  "tags": [
    "food"
  ],
  "alias": [
    "137752920269918"
  ],
  "places": [
    {
      "address": {
        "zh": "地址灣仔謝斐道392號維新大厦地下E鋪"
      },
      "googleMapsPlaceId": "ChIJZZRMUVcABDQRjb3F4505Neg"
    },
    {
      "address": {
        "zh": "西灣河聖十字徑38號鴻恩大廈地下7號舖"
      },
      "googleMapsPlaceId": "ChIJjZ1cYnYBBDQR4QEo5BqO5Uc"
    }
  ],
  "yellowBlueMapIds": [
    "Y_EAT00731",
    "Y_EAT00732"
  ]
}