{
  "id": "yanniemakeup",
  "name": {
    "en": "Yannie Cheung Makeup"
  },
  "webpages": [
    {
      "url": "https://yyimage.wixsite.com/yanniemakeup"
    },
    {
      "meta": {
        "id": "1453853211566920",
        "username": "yanniemakeup",
        "name": "Yannie Cheung Makeup",
        "about": "Yannie Cheung Makeup 化妝團隊提供各類化妝服務，多年經驗，為你帶來不一樣的?",
        "category_list": [
          {
            "id": "146059155460366",
            "name": "Makeup Artist"
          }
        ],
        "emails": [
          "yanyi1003@gmail.com"
        ],
        "single_line_address": "Ngau Tau Kok, Hong Kong",
        "website": "https://yyimage.wixsite.com/yanniemakeup",
        "link": "https://www.facebook.com/1453853211566920"
      },
      "url": "https://www.facebook.com/yanniemakeup/"
    },
    {
      "url": "https://www.instagram.com/yanniemakeup/",
      "meta": {
        "name": "YYIMAGE Yannie Cheung Makeup",
        "about": "𝕳𝖔𝖓𝖌 𝕶𝖔𝖓𝖌 𝕸𝖆𝖐𝖊𝖚𝖕 𝕬𝖗𝖙𝖎𝖘𝖙\nClick入呢條link WhatsApp快速查詢❤️👇🏻👇🏻"
      }
    }
  ],
  "posts": [
    {
      "url": "https://www.facebook.com/yanniemakeup/posts/2507595976192633"
    }
  ],
  "tags": [
    "makeup",
    "artist",
    "wedding"
  ],
  "places": [
    {
      "address": {
        "zh": "牛頭角海濱道139 – 141號海濱中心509室"
      },
      "googleMapsPlaceId": "ChIJQfBZf0gBBDQRcos0Yk-qKvs",
      "coordinates": {
        "lat": 22.3125627,
        "lng": 114.2179202
      },
      "area": {
        "zh": "觀塘區"
      }
    }
  ]
}