{
  "id": "craftword23",
  "name": {
    "zh": "字．作業"
  },
  "webpages": [
    {
      "meta": {
        "about": "文字本來就是最美麗的藝術品",
        "categories": [
          "Artist"
        ],
        "id": "410709619117793"
      },
      "url": "https://www.facebook.com/craftword23/"
    }
  ],
  "posts": [
    {
      "url": "https://www.facebook.com/craftword23/photos/a.495242207331200/1161569984031749/"
    },
    {
      "url": "https://www.facebook.com/craftword23/photos/a.495242207331200/1157340414454706/"
    }
  ],
  "tags": [
    "artist"
  ]
}